pidi/__init__.py
pidi/__main__.py
pidi/brainz.py
pidi/client.py
pidi/display.py
pidi/fifo.py
pidi/util.py
pidi-0.1.0.dist-info/LICENSE.txt
pidi-0.1.0.dist-info/METADATA
pidi-0.1.0.dist-info/WHEEL
pidi-0.1.0.dist-info/entry_points.txt
pidi-0.1.0.dist-info/top_level.txt
pidi-0.1.0.dist-info/RECORD
