Metadata-Version: 2.1
Name: pidi
Version: 0.1.0
Summary: Download and display album art for mpd tracks.
Home-page: https://www.pimoroni.com
Author: Philip Howard
Author-email: phil@pimoroni.com
License: MIT
Project-URL: GitHub, https://github.com/pimoroni/pidi
Project-URL: Twitter, https://twitter.com/pimoroni
Keywords: Mopidy mpd
Platform: any
Classifier: Environment :: X11 Applications
Classifier: License :: OSI Approved :: MIT License
Classifier: Operating System :: POSIX :: Linux
Classifier: Programming Language :: Python :: 3.6
Requires-Python: >=3.6
Requires-Dist: musicbrainzngs (>=0.7.1)
Requires-Dist: python-mpd2 (>=3.0.4)
Requires-Dist: untangle (>=1.1.1)
Provides-Extra: mpv
Requires-Dist: python-mpv (>=0.5.2) ; extra == 'mpv'
